{
  "states": [
    {
      "n": "Banteay Meanchey",
      "la": 13.75,
      "lo": 102.99,
      "sc": "1",
      "t": "province",
      "cities": [
        {
          "n": "Mongkol Borei",
          "la": 13.46,
          "lo": 102.99,
          "fn": "Mongkol Borei, Banteay Meanchey",
          "s": "Banteay Meanchey"
        },
        {
          "n": "Paoy Paet",
          "la": 13.66,
          "lo": 102.56,
          "fn": "Paoy Paet, Banteay Meanchey",
          "s": "Banteay Meanchey"
        },
        {
          "n": "Sisophon",
          "la": 13.59,
          "lo": 102.97,
          "fn": "Sisophon, Banteay Meanchey",
          "s": "Banteay Meanchey"
        },
        {
          "n": "Srŏk Malai",
          "la": 13.5,
          "lo": 102.6,
          "fn": "Srŏk Malai, Banteay Meanchey",
          "s": "Banteay Meanchey"
        },
        {
          "n": "Srŏk Svay Chék",
          "la": 13.81,
          "lo": 102.95,
          "fn": "Srŏk Svay Chék, Banteay Meanchey",
          "s": "Banteay Meanchey"
        }
      ]
    },
    {
      "n": "Banteay Meanchey",
      "la": 13.75,
      "lo": 102.99,
      "sc": "1",
      "t": "province",
      "cities": [
        {
          "n": "Mongkol Borei",
          "la": 13.46,
          "lo": 102.99,
          "fn": "Mongkol Borei, Banteay Meanchey",
          "s": "Banteay Meanchey"
        },
        {
          "n": "Paoy Paet",
          "la": 13.66,
          "lo": 102.56,
          "fn": "Paoy Paet, Banteay Meanchey",
          "s": "Banteay Meanchey"
        },
        {
          "n": "Sisophon",
          "la": 13.59,
          "lo": 102.97,
          "fn": "Sisophon, Banteay Meanchey",
          "s": "Banteay Meanchey"
        },
        {
          "n": "Srŏk Malai",
          "la": 13.5,
          "lo": 102.6,
          "fn": "Srŏk Malai, Banteay Meanchey",
          "s": "Banteay Meanchey"
        },
        {
          "n": "Srŏk Svay Chék",
          "la": 13.81,
          "lo": 102.95,
          "fn": "Srŏk Svay Chék, Banteay Meanchey",
          "s": "Banteay Meanchey"
        }
      ]
    },
    {
      "n": "Battambang",
      "la": 13.03,
      "lo": 102.99,
      "sc": "2",
      "t": "province",
      "cities": [
        {
          "n": "Battambang",
          "la": 13.1,
          "lo": 103.2,
          "fn": "Battambang, Battambang",
          "s": "Battambang"
        },
        {
          "n": "Srŏk Âk Phnŭm",
          "la": 13.24,
          "lo": 103.46,
          "fn": "Srŏk Âk Phnŭm, Battambang",
          "s": "Battambang"
        },
        {
          "n": "Srŏk Banăn",
          "la": 12.97,
          "lo": 103.05,
          "fn": "Srŏk Banăn, Battambang",
          "s": "Battambang"
        },
        {
          "n": "Srŏk Bâvĭl",
          "la": 13.24,
          "lo": 102.83,
          "fn": "Srŏk Bâvĭl, Battambang",
          "s": "Battambang"
        },
        {
          "n": "Srŏk Rotanak Mondol",
          "la": 12.84,
          "lo": 102.89,
          "fn": "Srŏk Rotanak Mondol, Battambang",
          "s": "Battambang"
        }
      ]
    },
    {
      "n": "Battambang",
      "la": 13.03,
      "lo": 102.99,
      "sc": "2",
      "t": "province",
      "cities": [
        {
          "n": "Battambang",
          "la": 13.1,
          "lo": 103.2,
          "fn": "Battambang, Battambang",
          "s": "Battambang"
        },
        {
          "n": "Srŏk Âk Phnŭm",
          "la": 13.24,
          "lo": 103.46,
          "fn": "Srŏk Âk Phnŭm, Battambang",
          "s": "Battambang"
        },
        {
          "n": "Srŏk Banăn",
          "la": 12.97,
          "lo": 103.05,
          "fn": "Srŏk Banăn, Battambang",
          "s": "Battambang"
        },
        {
          "n": "Srŏk Bâvĭl",
          "la": 13.24,
          "lo": 102.83,
          "fn": "Srŏk Bâvĭl, Battambang",
          "s": "Battambang"
        },
        {
          "n": "Srŏk Rotanak Mondol",
          "la": 12.84,
          "lo": 102.89,
          "fn": "Srŏk Rotanak Mondol, Battambang",
          "s": "Battambang"
        }
      ]
    },
    {
      "n": "Kampong Cham",
      "la": 12.1,
      "lo": 105.31,
      "sc": "3",
      "t": "province",
      "cities": [
        {
          "n": "Cheung Prey",
          "la": 12.1,
          "lo": 105.07,
          "fn": "Cheung Prey, Kampong Cham",
          "s": "Kampong Cham"
        },
        {
          "n": "Kampong Cham",
          "la": 11.98,
          "lo": 105.44,
          "fn": "Kampong Cham, Kampong Cham",
          "s": "Kampong Cham"
        },
        {
          "n": "Srŏk Bathéay",
          "la": 12.03,
          "lo": 104.93,
          "fn": "Srŏk Bathéay, Kampong Cham",
          "s": "Kampong Cham"
        }
      ]
    },
    {
      "n": "Kampong Cham",
      "la": 12.1,
      "lo": 105.31,
      "sc": "3",
      "t": "province",
      "cities": [
        {
          "n": "Cheung Prey",
          "la": 12.1,
          "lo": 105.07,
          "fn": "Cheung Prey, Kampong Cham",
          "s": "Kampong Cham"
        },
        {
          "n": "Kampong Cham",
          "la": 11.98,
          "lo": 105.44,
          "fn": "Kampong Cham, Kampong Cham",
          "s": "Kampong Cham"
        },
        {
          "n": "Srŏk Bathéay",
          "la": 12.03,
          "lo": 104.93,
          "fn": "Srŏk Bathéay, Kampong Cham",
          "s": "Kampong Cham"
        }
      ]
    },
    {
      "n": "Kampong Chhnang",
      "la": 12.14,
      "lo": 104.57,
      "sc": "4",
      "t": "province",
      "cities": [
        {
          "n": "Baribour",
          "la": 12.43,
          "lo": 104.47,
          "fn": "Baribour, Kampong Chhnang",
          "s": "Kampong Chhnang"
        },
        {
          "n": "Kampong Chhnang",
          "la": 12.26,
          "lo": 104.67,
          "fn": "Kampong Chhnang, Kampong Chhnang",
          "s": "Kampong Chhnang"
        },
        {
          "n": "Rolea B'ier",
          "la": 12.21,
          "lo": 104.61,
          "fn": "Rolea B'ier, Kampong Chhnang",
          "s": "Kampong Chhnang"
        },
        {
          "n": "Srŏk Chol Kiri",
          "la": 12.16,
          "lo": 104.82,
          "fn": "Srŏk Chol Kiri, Kampong Chhnang",
          "s": "Kampong Chhnang"
        },
        {
          "n": "Srŏk Sameakki Mean Chey",
          "la": 11.87,
          "lo": 104.56,
          "fn": "Srŏk Sameakki Mean Chey, Kampong Chhnang",
          "s": "Kampong Chhnang"
        }
      ]
    },
    {
      "n": "Kampong Chhnang",
      "la": 12.14,
      "lo": 104.57,
      "sc": "4",
      "t": "province",
      "cities": [
        {
          "n": "Baribour",
          "la": 12.43,
          "lo": 104.47,
          "fn": "Baribour, Kampong Chhnang",
          "s": "Kampong Chhnang"
        },
        {
          "n": "Kampong Chhnang",
          "la": 12.26,
          "lo": 104.67,
          "fn": "Kampong Chhnang, Kampong Chhnang",
          "s": "Kampong Chhnang"
        },
        {
          "n": "Rolea B'ier",
          "la": 12.21,
          "lo": 104.61,
          "fn": "Rolea B'ier, Kampong Chhnang",
          "s": "Kampong Chhnang"
        },
        {
          "n": "Srŏk Chol Kiri",
          "la": 12.16,
          "lo": 104.82,
          "fn": "Srŏk Chol Kiri, Kampong Chhnang",
          "s": "Kampong Chhnang"
        },
        {
          "n": "Srŏk Sameakki Mean Chey",
          "la": 11.87,
          "lo": 104.56,
          "fn": "Srŏk Sameakki Mean Chey, Kampong Chhnang",
          "s": "Kampong Chhnang"
        }
      ]
    },
    {
      "n": "Kampong Speu",
      "la": 11.62,
      "lo": 104.38,
      "sc": "5",
      "t": "province",
      "cities": [
        {
          "n": "Kampong Speu",
          "la": 11.45,
          "lo": 104.52,
          "fn": "Kampong Speu, Kampong Speu",
          "s": "Kampong Speu"
        },
        {
          "n": "Krŏng Chbar Mon",
          "la": 11.47,
          "lo": 104.51,
          "fn": "Krŏng Chbar Mon, Kampong Speu",
          "s": "Kampong Speu"
        },
        {
          "n": "Srŏk Basedth",
          "la": 11.18,
          "lo": 104.54,
          "fn": "Srŏk Basedth, Kampong Speu",
          "s": "Kampong Speu"
        },
        {
          "n": "Srŏk Kông Pĭsei",
          "la": 11.32,
          "lo": 104.66,
          "fn": "Srŏk Kông Pĭsei, Kampong Speu",
          "s": "Kampong Speu"
        },
        {
          "n": "Srŏk Ŏdŏngk",
          "la": 11.67,
          "lo": 104.61,
          "fn": "Srŏk Ŏdŏngk, Kampong Speu",
          "s": "Kampong Speu"
        }
      ]
    },
    {
      "n": "Kampong Speu",
      "la": 11.62,
      "lo": 104.38,
      "sc": "5",
      "t": "province",
      "cities": [
        {
          "n": "Kampong Speu",
          "la": 11.45,
          "lo": 104.52,
          "fn": "Kampong Speu, Kampong Speu",
          "s": "Kampong Speu"
        },
        {
          "n": "Krŏng Chbar Mon",
          "la": 11.47,
          "lo": 104.51,
          "fn": "Krŏng Chbar Mon, Kampong Speu",
          "s": "Kampong Speu"
        },
        {
          "n": "Srŏk Basedth",
          "la": 11.18,
          "lo": 104.54,
          "fn": "Srŏk Basedth, Kampong Speu",
          "s": "Kampong Speu"
        },
        {
          "n": "Srŏk Kông Pĭsei",
          "la": 11.32,
          "lo": 104.66,
          "fn": "Srŏk Kông Pĭsei, Kampong Speu",
          "s": "Kampong Speu"
        },
        {
          "n": "Srŏk Ŏdŏngk",
          "la": 11.67,
          "lo": 104.61,
          "fn": "Srŏk Ŏdŏngk, Kampong Speu",
          "s": "Kampong Speu"
        }
      ]
    },
    {
      "n": "Kampong Thom",
      "la": 12.82,
      "lo": 103.84,
      "sc": "6",
      "t": "province",
      "cities": []
    },
    {
      "n": "Kampong Thom",
      "la": 12.82,
      "lo": 103.84,
      "sc": "6",
      "t": "province",
      "cities": []
    },
    {
      "n": "Kampot",
      "la": 10.73,
      "lo": 104.38,
      "sc": "7",
      "t": "province",
      "cities": [
        {
          "n": "Angkor Chey",
          "la": 10.77,
          "lo": 104.65,
          "fn": "Angkor Chey, Kampot",
          "s": "Kampot"
        },
        {
          "n": "Banteay Meas",
          "la": 10.62,
          "lo": 104.53,
          "fn": "Banteay Meas, Kampot",
          "s": "Kampot"
        },
        {
          "n": "Chhouk District",
          "la": 10.82,
          "lo": 104.45,
          "fn": "Chhouk District, Kampot",
          "s": "Kampot"
        },
        {
          "n": "Kampong Bay",
          "la": 10.6,
          "lo": 104.17,
          "fn": "Kampong Bay, Kampot",
          "s": "Kampot"
        },
        {
          "n": "Kampong Tranch",
          "la": 10.55,
          "lo": 104.47,
          "fn": "Kampong Tranch, Kampot",
          "s": "Kampot"
        },
        {
          "n": "Kampot",
          "la": 10.61,
          "lo": 104.18,
          "fn": "Kampot, Kampot",
          "s": "Kampot"
        },
        {
          "n": "Srŏk Chŭm Kiri",
          "la": 11.01,
          "lo": 104.44,
          "fn": "Srŏk Chŭm Kiri, Kampot",
          "s": "Kampot"
        },
        {
          "n": "Srŏk Dângtóng",
          "la": 10.71,
          "lo": 104.42,
          "fn": "Srŏk Dângtóng, Kampot",
          "s": "Kampot"
        },
        {
          "n": "Srok Tuek Chhou",
          "la": 10.75,
          "lo": 104.11,
          "fn": "Srok Tuek Chhou, Kampot",
          "s": "Kampot"
        }
      ]
    },
    {
      "n": "Kampot",
      "la": 10.73,
      "lo": 104.38,
      "sc": "7",
      "t": "province",
      "cities": [
        {
          "n": "Angkor Chey",
          "la": 10.77,
          "lo": 104.65,
          "fn": "Angkor Chey, Kampot",
          "s": "Kampot"
        },
        {
          "n": "Banteay Meas",
          "la": 10.62,
          "lo": 104.53,
          "fn": "Banteay Meas, Kampot",
          "s": "Kampot"
        },
        {
          "n": "Chhouk District",
          "la": 10.82,
          "lo": 104.45,
          "fn": "Chhouk District, Kampot",
          "s": "Kampot"
        },
        {
          "n": "Kampong Bay",
          "la": 10.6,
          "lo": 104.17,
          "fn": "Kampong Bay, Kampot",
          "s": "Kampot"
        },
        {
          "n": "Kampong Tranch",
          "la": 10.55,
          "lo": 104.47,
          "fn": "Kampong Tranch, Kampot",
          "s": "Kampot"
        },
        {
          "n": "Kampot",
          "la": 10.61,
          "lo": 104.18,
          "fn": "Kampot, Kampot",
          "s": "Kampot"
        },
        {
          "n": "Srŏk Chŭm Kiri",
          "la": 11.01,
          "lo": 104.44,
          "fn": "Srŏk Chŭm Kiri, Kampot",
          "s": "Kampot"
        },
        {
          "n": "Srŏk Dângtóng",
          "la": 10.71,
          "lo": 104.42,
          "fn": "Srŏk Dângtóng, Kampot",
          "s": "Kampot"
        },
        {
          "n": "Srok Tuek Chhou",
          "la": 10.75,
          "lo": 104.11,
          "fn": "Srok Tuek Chhou, Kampot",
          "s": "Kampot"
        }
      ]
    },
    {
      "n": "Kandal",
      "la": 11.22,
      "lo": 105.13,
      "sc": "8",
      "t": "province",
      "cities": [
        {
          "n": "Krŏng Ta Khmau",
          "la": 11.45,
          "lo": 104.94,
          "fn": "Krŏng Ta Khmau, Kandal",
          "s": "Kandal"
        },
        {
          "n": "Srŏk Khsăch Kândal",
          "la": 11.69,
          "lo": 105.04,
          "fn": "Srŏk Khsăch Kândal, Kandal",
          "s": "Kandal"
        },
        {
          "n": "Ta Khmau",
          "la": 11.48,
          "lo": 104.95,
          "fn": "Ta Khmau, Kandal",
          "s": "Kandal"
        }
      ]
    },
    {
      "n": "Kandal",
      "la": 11.22,
      "lo": 105.13,
      "sc": "8",
      "t": "province",
      "cities": [
        {
          "n": "Krŏng Ta Khmau",
          "la": 11.45,
          "lo": 104.94,
          "fn": "Krŏng Ta Khmau, Kandal",
          "s": "Kandal"
        },
        {
          "n": "Srŏk Khsăch Kândal",
          "la": 11.69,
          "lo": 105.04,
          "fn": "Srŏk Khsăch Kândal, Kandal",
          "s": "Kandal"
        },
        {
          "n": "Ta Khmau",
          "la": 11.48,
          "lo": 104.95,
          "fn": "Ta Khmau, Kandal",
          "s": "Kandal"
        }
      ]
    },
    {
      "n": "Kep",
      "la": 10.54,
      "lo": 104.36,
      "sc": "23",
      "t": "province",
      "cities": [
        {
          "n": "Krong Kep",
          "la": 10.48,
          "lo": 104.32,
          "fn": "Krong Kep, Kep",
          "s": "Kep"
        },
        {
          "n": "Srŏk Dâmnăk Châng’aeur",
          "la": 10.53,
          "lo": 104.35,
          "fn": "Srŏk Dâmnăk Châng’aeur, Kep",
          "s": "Kep"
        }
      ]
    },
    {
      "n": "Kep",
      "la": 10.54,
      "lo": 104.36,
      "sc": "23",
      "t": "province",
      "cities": [
        {
          "n": "Krong Kep",
          "la": 10.48,
          "lo": 104.32,
          "fn": "Krong Kep, Kep",
          "s": "Kep"
        },
        {
          "n": "Srŏk Dâmnăk Châng’aeur",
          "la": 10.53,
          "lo": 104.35,
          "fn": "Srŏk Dâmnăk Châng’aeur, Kep",
          "s": "Kep"
        }
      ]
    },
    {
      "n": "Koh Kong",
      "la": 11.58,
      "lo": 103.36,
      "sc": "9",
      "t": "province",
      "cities": [
        {
          "n": "Koh Kong",
          "la": 11.62,
          "lo": 102.98,
          "fn": "Koh Kong, Koh Kong",
          "s": "Koh Kong"
        },
        {
          "n": "Smach Mean Chey",
          "la": 11.55,
          "lo": 103.04,
          "fn": "Smach Mean Chey, Koh Kong",
          "s": "Koh Kong"
        },
        {
          "n": "Srae Ambel",
          "la": 11.11,
          "lo": 103.76,
          "fn": "Srae Ambel, Koh Kong",
          "s": "Koh Kong"
        },
        {
          "n": "Srŏk Batum Sakôr",
          "la": 11.11,
          "lo": 103.39,
          "fn": "Srŏk Batum Sakôr, Koh Kong",
          "s": "Koh Kong"
        },
        {
          "n": "Srŏk Môndôl Seima",
          "la": 11.81,
          "lo": 103.01,
          "fn": "Srŏk Môndôl Seima, Koh Kong",
          "s": "Koh Kong"
        }
      ]
    },
    {
      "n": "Koh Kong",
      "la": 11.58,
      "lo": 103.36,
      "sc": "9",
      "t": "province",
      "cities": [
        {
          "n": "Koh Kong",
          "la": 11.62,
          "lo": 102.98,
          "fn": "Koh Kong, Koh Kong",
          "s": "Koh Kong"
        },
        {
          "n": "Smach Mean Chey",
          "la": 11.55,
          "lo": 103.04,
          "fn": "Smach Mean Chey, Koh Kong",
          "s": "Koh Kong"
        },
        {
          "n": "Srae Ambel",
          "la": 11.11,
          "lo": 103.76,
          "fn": "Srae Ambel, Koh Kong",
          "s": "Koh Kong"
        },
        {
          "n": "Srŏk Batum Sakôr",
          "la": 11.11,
          "lo": 103.39,
          "fn": "Srŏk Batum Sakôr, Koh Kong",
          "s": "Koh Kong"
        },
        {
          "n": "Srŏk Môndôl Seima",
          "la": 11.81,
          "lo": 103.01,
          "fn": "Srŏk Môndôl Seima, Koh Kong",
          "s": "Koh Kong"
        }
      ]
    },
    {
      "n": "Kratie",
      "la": 12.5,
      "lo": 105.97,
      "sc": "10",
      "t": "province",
      "cities": [
        {
          "n": "Kracheh",
          "la": 12.57,
          "lo": 106.2,
          "fn": "Kracheh, Kratie",
          "s": "Kratie"
        },
        {
          "n": "Kratié",
          "la": 12.49,
          "lo": 106.02,
          "fn": "Kratié, Kratie",
          "s": "Kratie"
        },
        {
          "n": "Snuol",
          "la": 12.19,
          "lo": 106.47,
          "fn": "Snuol, Kratie",
          "s": "Kratie"
        }
      ]
    },
    {
      "n": "Kratie",
      "la": 12.5,
      "lo": 105.97,
      "sc": "10",
      "t": "province",
      "cities": [
        {
          "n": "Kracheh",
          "la": 12.57,
          "lo": 106.2,
          "fn": "Kracheh, Kratie",
          "s": "Kratie"
        },
        {
          "n": "Kratié",
          "la": 12.49,
          "lo": 106.02,
          "fn": "Kratié, Kratie",
          "s": "Kratie"
        },
        {
          "n": "Snuol",
          "la": 12.19,
          "lo": 106.47,
          "fn": "Snuol, Kratie",
          "s": "Kratie"
        }
      ]
    },
    {
      "n": "Mondulkiri",
      "la": 12.79,
      "lo": 107.1,
      "sc": "11",
      "t": "province",
      "cities": [
        {
          "n": "Krŏng Sênmônoŭrôm",
          "la": 12.5,
          "lo": 107.16,
          "fn": "Krŏng Sênmônoŭrôm, Mondulkiri",
          "s": "Mondulkiri"
        },
        {
          "n": "Sen Monorom",
          "la": 12.46,
          "lo": 107.19,
          "fn": "Sen Monorom, Mondulkiri",
          "s": "Mondulkiri"
        },
        {
          "n": "Srŏk Kaev Seima",
          "la": 12.42,
          "lo": 106.77,
          "fn": "Srŏk Kaev Seima, Mondulkiri",
          "s": "Mondulkiri"
        },
        {
          "n": "Srŏk Pech Chreada",
          "la": 12.73,
          "lo": 107.09,
          "fn": "Srŏk Pech Chreada, Mondulkiri",
          "s": "Mondulkiri"
        }
      ]
    },
    {
      "n": "Mondulkiri",
      "la": 12.79,
      "lo": 107.1,
      "sc": "11",
      "t": "province",
      "cities": [
        {
          "n": "Krŏng Sênmônoŭrôm",
          "la": 12.5,
          "lo": 107.16,
          "fn": "Krŏng Sênmônoŭrôm, Mondulkiri",
          "s": "Mondulkiri"
        },
        {
          "n": "Sen Monorom",
          "la": 12.46,
          "lo": 107.19,
          "fn": "Sen Monorom, Mondulkiri",
          "s": "Mondulkiri"
        },
        {
          "n": "Srŏk Kaev Seima",
          "la": 12.42,
          "lo": 106.77,
          "fn": "Srŏk Kaev Seima, Mondulkiri",
          "s": "Mondulkiri"
        },
        {
          "n": "Srŏk Pech Chreada",
          "la": 12.73,
          "lo": 107.09,
          "fn": "Srŏk Pech Chreada, Mondulkiri",
          "s": "Mondulkiri"
        }
      ]
    },
    {
      "n": "Oddar Meanchey",
      "la": 14.16,
      "lo": 103.82,
      "sc": "22",
      "t": "province",
      "cities": [
        {
          "n": "Samraong",
          "la": 14.18,
          "lo": 103.52,
          "fn": "Samraong, Oddar Meanchey",
          "s": "Oddar Meanchey"
        },
        {
          "n": "Srŏk Bântéay Âmpĭl",
          "la": 14.19,
          "lo": 103.26,
          "fn": "Srŏk Bântéay Âmpĭl, Oddar Meanchey",
          "s": "Oddar Meanchey"
        },
        {
          "n": "Srŏk Sâmraông",
          "la": 14.25,
          "lo": 103.63,
          "fn": "Srŏk Sâmraông, Oddar Meanchey",
          "s": "Oddar Meanchey"
        },
        {
          "n": "Srŏk Trâpeăng Prasat",
          "la": 14.26,
          "lo": 104.31,
          "fn": "Srŏk Trâpeăng Prasat, Oddar Meanchey",
          "s": "Oddar Meanchey"
        }
      ]
    },
    {
      "n": "Oddar Meanchey",
      "la": 14.16,
      "lo": 103.82,
      "sc": "22",
      "t": "province",
      "cities": [
        {
          "n": "Samraong",
          "la": 14.18,
          "lo": 103.52,
          "fn": "Samraong, Oddar Meanchey",
          "s": "Oddar Meanchey"
        },
        {
          "n": "Srŏk Bântéay Âmpĭl",
          "la": 14.19,
          "lo": 103.26,
          "fn": "Srŏk Bântéay Âmpĭl, Oddar Meanchey",
          "s": "Oddar Meanchey"
        },
        {
          "n": "Srŏk Sâmraông",
          "la": 14.25,
          "lo": 103.63,
          "fn": "Srŏk Sâmraông, Oddar Meanchey",
          "s": "Oddar Meanchey"
        },
        {
          "n": "Srŏk Trâpeăng Prasat",
          "la": 14.26,
          "lo": 104.31,
          "fn": "Srŏk Trâpeăng Prasat, Oddar Meanchey",
          "s": "Oddar Meanchey"
        }
      ]
    },
    {
      "n": "Pailin",
      "la": 12.91,
      "lo": 102.67,
      "sc": "24",
      "t": "province",
      "cities": [
        {
          "n": "Khan Sala Krau",
          "la": 12.98,
          "lo": 102.64,
          "fn": "Khan Sala Krau, Pailin",
          "s": "Pailin"
        },
        {
          "n": "Pailin",
          "la": 12.85,
          "lo": 102.61,
          "fn": "Pailin, Pailin",
          "s": "Pailin"
        }
      ]
    },
    {
      "n": "Pailin",
      "la": 12.91,
      "lo": 102.67,
      "sc": "24",
      "t": "province",
      "cities": [
        {
          "n": "Khan Sala Krau",
          "la": 12.98,
          "lo": 102.64,
          "fn": "Khan Sala Krau, Pailin",
          "s": "Pailin"
        },
        {
          "n": "Pailin",
          "la": 12.85,
          "lo": 102.61,
          "fn": "Pailin, Pailin",
          "s": "Pailin"
        }
      ]
    },
    {
      "n": "Phnom Penh",
      "la": 11.56,
      "lo": 104.93,
      "sc": "12",
      "t": "autonomous municipality",
      "cities": [
        {
          "n": "Khan 7 Makara",
          "la": 11.56,
          "lo": 104.91,
          "fn": "Khan 7 Makara, Phnom Penh",
          "s": "Phnom Penh"
        },
        {
          "n": "Khan Châmkar Mon",
          "la": 11.54,
          "lo": 104.92,
          "fn": "Khan Châmkar Mon, Phnom Penh",
          "s": "Phnom Penh"
        },
        {
          "n": "Khan Dângkaô",
          "la": 11.52,
          "lo": 104.84,
          "fn": "Khan Dângkaô, Phnom Penh",
          "s": "Phnom Penh"
        },
        {
          "n": "Khan Duŏn Pénh",
          "la": 11.58,
          "lo": 104.92,
          "fn": "Khan Duŏn Pénh, Phnom Penh",
          "s": "Phnom Penh"
        },
        {
          "n": "Khan Méan Chey",
          "la": 11.52,
          "lo": 104.95,
          "fn": "Khan Méan Chey, Phnom Penh",
          "s": "Phnom Penh"
        },
        {
          "n": "Khan Russey Keo",
          "la": 11.62,
          "lo": 104.91,
          "fn": "Khan Russey Keo, Phnom Penh",
          "s": "Phnom Penh"
        },
        {
          "n": "Khan Saen Sokh",
          "la": 11.61,
          "lo": 104.86,
          "fn": "Khan Saen Sokh, Phnom Penh",
          "s": "Phnom Penh"
        },
        {
          "n": "Phnom Penh",
          "la": 11.56,
          "lo": 104.92,
          "fn": "Phnom Penh, Phnom Penh",
          "s": "Phnom Penh"
        }
      ]
    },
    {
      "n": "Phnom Penh",
      "la": 11.56,
      "lo": 104.93,
      "sc": "12",
      "t": "autonomous municipality",
      "cities": [
        {
          "n": "Khan 7 Makara",
          "la": 11.56,
          "lo": 104.91,
          "fn": "Khan 7 Makara, Phnom Penh",
          "s": "Phnom Penh"
        },
        {
          "n": "Khan Châmkar Mon",
          "la": 11.54,
          "lo": 104.92,
          "fn": "Khan Châmkar Mon, Phnom Penh",
          "s": "Phnom Penh"
        },
        {
          "n": "Khan Dângkaô",
          "la": 11.52,
          "lo": 104.84,
          "fn": "Khan Dângkaô, Phnom Penh",
          "s": "Phnom Penh"
        },
        {
          "n": "Khan Duŏn Pénh",
          "la": 11.58,
          "lo": 104.92,
          "fn": "Khan Duŏn Pénh, Phnom Penh",
          "s": "Phnom Penh"
        },
        {
          "n": "Khan Méan Chey",
          "la": 11.52,
          "lo": 104.95,
          "fn": "Khan Méan Chey, Phnom Penh",
          "s": "Phnom Penh"
        },
        {
          "n": "Khan Russey Keo",
          "la": 11.62,
          "lo": 104.91,
          "fn": "Khan Russey Keo, Phnom Penh",
          "s": "Phnom Penh"
        },
        {
          "n": "Khan Saen Sokh",
          "la": 11.61,
          "lo": 104.86,
          "fn": "Khan Saen Sokh, Phnom Penh",
          "s": "Phnom Penh"
        },
        {
          "n": "Phnom Penh",
          "la": 11.56,
          "lo": 104.92,
          "fn": "Phnom Penh, Phnom Penh",
          "s": "Phnom Penh"
        }
      ]
    },
    {
      "n": "Preah Vihear",
      "la": 14.01,
      "lo": 104.85,
      "sc": "13",
      "t": "province",
      "cities": [
        {
          "n": "Sangkom Thmei",
          "la": 13.47,
          "lo": 104.77,
          "fn": "Sangkom Thmei, Preah Vihear",
          "s": "Preah Vihear"
        },
        {
          "n": "Srŏk Ch’êh Sên",
          "la": 13.58,
          "lo": 105.35,
          "fn": "Srŏk Ch’êh Sên, Preah Vihear",
          "s": "Preah Vihear"
        },
        {
          "n": "Srŏk Chhêb",
          "la": 13.91,
          "lo": 105.46,
          "fn": "Srŏk Chhêb, Preah Vihear",
          "s": "Preah Vihear"
        },
        {
          "n": "Srŏk Kulén",
          "la": 13.79,
          "lo": 104.61,
          "fn": "Srŏk Kulén, Preah Vihear",
          "s": "Preah Vihear"
        },
        {
          "n": "Srŏk Rôviĕng",
          "la": 13.35,
          "lo": 105.1,
          "fn": "Srŏk Rôviĕng, Preah Vihear",
          "s": "Preah Vihear"
        },
        {
          "n": "Srŏk Tbêng Méanchey",
          "la": 13.79,
          "lo": 105.02,
          "fn": "Srŏk Tbêng Méanchey, Preah Vihear",
          "s": "Preah Vihear"
        },
        {
          "n": "Tbeng Meanchey",
          "la": 13.81,
          "lo": 104.98,
          "fn": "Tbeng Meanchey, Preah Vihear",
          "s": "Preah Vihear"
        }
      ]
    },
    {
      "n": "Preah Vihear",
      "la": 14.01,
      "lo": 104.85,
      "sc": "13",
      "t": "province",
      "cities": [
        {
          "n": "Sangkom Thmei",
          "la": 13.47,
          "lo": 104.77,
          "fn": "Sangkom Thmei, Preah Vihear",
          "s": "Preah Vihear"
        },
        {
          "n": "Srŏk Ch’êh Sên",
          "la": 13.58,
          "lo": 105.35,
          "fn": "Srŏk Ch’êh Sên, Preah Vihear",
          "s": "Preah Vihear"
        },
        {
          "n": "Srŏk Chhêb",
          "la": 13.91,
          "lo": 105.46,
          "fn": "Srŏk Chhêb, Preah Vihear",
          "s": "Preah Vihear"
        },
        {
          "n": "Srŏk Kulén",
          "la": 13.79,
          "lo": 104.61,
          "fn": "Srŏk Kulén, Preah Vihear",
          "s": "Preah Vihear"
        },
        {
          "n": "Srŏk Rôviĕng",
          "la": 13.35,
          "lo": 105.1,
          "fn": "Srŏk Rôviĕng, Preah Vihear",
          "s": "Preah Vihear"
        },
        {
          "n": "Srŏk Tbêng Méanchey",
          "la": 13.79,
          "lo": 105.02,
          "fn": "Srŏk Tbêng Méanchey, Preah Vihear",
          "s": "Preah Vihear"
        },
        {
          "n": "Tbeng Meanchey",
          "la": 13.81,
          "lo": 104.98,
          "fn": "Tbeng Meanchey, Preah Vihear",
          "s": "Preah Vihear"
        }
      ]
    },
    {
      "n": "Prey Veng",
      "la": 11.38,
      "lo": 105.5,
      "sc": "14",
      "t": "province",
      "cities": [
        {
          "n": "Prey Veng",
          "la": 11.49,
          "lo": 105.33,
          "fn": "Prey Veng, Prey Veng",
          "s": "Prey Veng"
        },
        {
          "n": "Srŏk Kâmpóng Léav",
          "la": 11.51,
          "lo": 105.3,
          "fn": "Srŏk Kâmpóng Léav, Prey Veng",
          "s": "Prey Veng"
        },
        {
          "n": "Srŏk Mésang",
          "la": 11.36,
          "lo": 105.57,
          "fn": "Srŏk Mésang, Prey Veng",
          "s": "Prey Veng"
        },
        {
          "n": "Srŏk Preăh Sdéch",
          "la": 11.09,
          "lo": 105.37,
          "fn": "Srŏk Preăh Sdéch, Prey Veng",
          "s": "Prey Veng"
        }
      ]
    },
    {
      "n": "Prey Veng",
      "la": 11.38,
      "lo": 105.5,
      "sc": "14",
      "t": "province",
      "cities": [
        {
          "n": "Prey Veng",
          "la": 11.49,
          "lo": 105.33,
          "fn": "Prey Veng, Prey Veng",
          "s": "Prey Veng"
        },
        {
          "n": "Srŏk Kâmpóng Léav",
          "la": 11.51,
          "lo": 105.3,
          "fn": "Srŏk Kâmpóng Léav, Prey Veng",
          "s": "Prey Veng"
        },
        {
          "n": "Srŏk Mésang",
          "la": 11.36,
          "lo": 105.57,
          "fn": "Srŏk Mésang, Prey Veng",
          "s": "Prey Veng"
        },
        {
          "n": "Srŏk Preăh Sdéch",
          "la": 11.09,
          "lo": 105.37,
          "fn": "Srŏk Preăh Sdéch, Prey Veng",
          "s": "Prey Veng"
        }
      ]
    },
    {
      "n": "Pursat",
      "la": 12.27,
      "lo": 103.73,
      "sc": "15",
      "t": "province",
      "cities": [
        {
          "n": "Bakan",
          "la": 12.78,
          "lo": 103.79,
          "fn": "Bakan, Pursat",
          "s": "Pursat"
        },
        {
          "n": "Krakor",
          "la": 12.48,
          "lo": 104.19,
          "fn": "Krakor, Pursat",
          "s": "Pursat"
        },
        {
          "n": "Pursat",
          "la": 12.54,
          "lo": 103.92,
          "fn": "Pursat, Pursat",
          "s": "Pursat"
        },
        {
          "n": "Sampov Meas",
          "la": 12.47,
          "lo": 103.92,
          "fn": "Sampov Meas, Pursat",
          "s": "Pursat"
        },
        {
          "n": "Srŏk Kândiĕng",
          "la": 12.71,
          "lo": 104.03,
          "fn": "Srŏk Kândiĕng, Pursat",
          "s": "Pursat"
        },
        {
          "n": "Srŏk Véal Vêng",
          "la": 12.24,
          "lo": 103.13,
          "fn": "Srŏk Véal Vêng, Pursat",
          "s": "Pursat"
        }
      ]
    },
    {
      "n": "Pursat",
      "la": 12.27,
      "lo": 103.73,
      "sc": "15",
      "t": "province",
      "cities": [
        {
          "n": "Bakan",
          "la": 12.78,
          "lo": 103.79,
          "fn": "Bakan, Pursat",
          "s": "Pursat"
        },
        {
          "n": "Krakor",
          "la": 12.48,
          "lo": 104.19,
          "fn": "Krakor, Pursat",
          "s": "Pursat"
        },
        {
          "n": "Pursat",
          "la": 12.54,
          "lo": 103.92,
          "fn": "Pursat, Pursat",
          "s": "Pursat"
        },
        {
          "n": "Sampov Meas",
          "la": 12.47,
          "lo": 103.92,
          "fn": "Sampov Meas, Pursat",
          "s": "Pursat"
        },
        {
          "n": "Srŏk Kândiĕng",
          "la": 12.71,
          "lo": 104.03,
          "fn": "Srŏk Kândiĕng, Pursat",
          "s": "Pursat"
        },
        {
          "n": "Srŏk Véal Vêng",
          "la": 12.24,
          "lo": 103.13,
          "fn": "Srŏk Véal Vêng, Pursat",
          "s": "Pursat"
        }
      ]
    },
    {
      "n": "Ratanakiri",
      "la": 13.86,
      "lo": 107.1,
      "sc": "16",
      "t": "province",
      "cities": [
        {
          "n": "Banlung",
          "la": 13.74,
          "lo": 106.99,
          "fn": "Banlung, Ratanakiri",
          "s": "Ratanakiri"
        },
        {
          "n": "Lumphat",
          "la": 13.49,
          "lo": 106.98,
          "fn": "Lumphat, Ratanakiri",
          "s": "Ratanakiri"
        },
        {
          "n": "Srŏk Ândong Méas",
          "la": 13.93,
          "lo": 107.31,
          "fn": "Srŏk Ândong Méas, Ratanakiri",
          "s": "Ratanakiri"
        },
        {
          "n": "Srŏk Bâ Kêv",
          "la": 13.71,
          "lo": 107.19,
          "fn": "Srŏk Bâ Kêv, Ratanakiri",
          "s": "Ratanakiri"
        },
        {
          "n": "Srŏk Ban Lŭng",
          "la": 13.68,
          "lo": 107.03,
          "fn": "Srŏk Ban Lŭng, Ratanakiri",
          "s": "Ratanakiri"
        },
        {
          "n": "Srŏk Koun Mom",
          "la": 13.52,
          "lo": 106.75,
          "fn": "Srŏk Koun Mom, Ratanakiri",
          "s": "Ratanakiri"
        },
        {
          "n": "Srŏk Ou Chum",
          "la": 13.84,
          "lo": 107.03,
          "fn": "Srŏk Ou Chum, Ratanakiri",
          "s": "Ratanakiri"
        },
        {
          "n": "Srŏk Ou Ya Dav",
          "la": 13.54,
          "lo": 107.45,
          "fn": "Srŏk Ou Ya Dav, Ratanakiri",
          "s": "Ratanakiri"
        },
        {
          "n": "Srŏk Ta Vêng",
          "la": 14.29,
          "lo": 107.24,
          "fn": "Srŏk Ta Vêng, Ratanakiri",
          "s": "Ratanakiri"
        }
      ]
    },
    {
      "n": "Ratanakiri",
      "la": 13.86,
      "lo": 107.1,
      "sc": "16",
      "t": "province",
      "cities": [
        {
          "n": "Banlung",
          "la": 13.74,
          "lo": 106.99,
          "fn": "Banlung, Ratanakiri",
          "s": "Ratanakiri"
        },
        {
          "n": "Lumphat",
          "la": 13.49,
          "lo": 106.98,
          "fn": "Lumphat, Ratanakiri",
          "s": "Ratanakiri"
        },
        {
          "n": "Srŏk Ândong Méas",
          "la": 13.93,
          "lo": 107.31,
          "fn": "Srŏk Ândong Méas, Ratanakiri",
          "s": "Ratanakiri"
        },
        {
          "n": "Srŏk Bâ Kêv",
          "la": 13.71,
          "lo": 107.19,
          "fn": "Srŏk Bâ Kêv, Ratanakiri",
          "s": "Ratanakiri"
        },
        {
          "n": "Srŏk Ban Lŭng",
          "la": 13.68,
          "lo": 107.03,
          "fn": "Srŏk Ban Lŭng, Ratanakiri",
          "s": "Ratanakiri"
        },
        {
          "n": "Srŏk Koun Mom",
          "la": 13.52,
          "lo": 106.75,
          "fn": "Srŏk Koun Mom, Ratanakiri",
          "s": "Ratanakiri"
        },
        {
          "n": "Srŏk Ou Chum",
          "la": 13.84,
          "lo": 107.03,
          "fn": "Srŏk Ou Chum, Ratanakiri",
          "s": "Ratanakiri"
        },
        {
          "n": "Srŏk Ou Ya Dav",
          "la": 13.54,
          "lo": 107.45,
          "fn": "Srŏk Ou Ya Dav, Ratanakiri",
          "s": "Ratanakiri"
        },
        {
          "n": "Srŏk Ta Vêng",
          "la": 14.29,
          "lo": 107.24,
          "fn": "Srŏk Ta Vêng, Ratanakiri",
          "s": "Ratanakiri"
        }
      ]
    },
    {
      "n": "Siem Reap",
      "la": 13.33,
      "lo": 104.1,
      "sc": "17",
      "t": "province",
      "cities": [
        {
          "n": "Siem Reap",
          "la": 13.36,
          "lo": 103.86,
          "fn": "Siem Reap, Siem Reap",
          "s": "Siem Reap"
        },
        {
          "n": "Srŏk Ângkôr Thum",
          "la": 13.58,
          "lo": 103.86,
          "fn": "Srŏk Ângkôr Thum, Siem Reap",
          "s": "Siem Reap"
        },
        {
          "n": "Srŏk Prasat Bakong",
          "la": 13.21,
          "lo": 103.98,
          "fn": "Srŏk Prasat Bakong, Siem Reap",
          "s": "Siem Reap"
        },
        {
          "n": "Svay Leu",
          "la": 13.69,
          "lo": 104.27,
          "fn": "Svay Leu, Siem Reap",
          "s": "Siem Reap"
        },
        {
          "n": "Varin",
          "la": 13.84,
          "lo": 103.9,
          "fn": "Varin, Siem Reap",
          "s": "Siem Reap"
        }
      ]
    },
    {
      "n": "Siem Reap",
      "la": 13.33,
      "lo": 104.1,
      "sc": "17",
      "t": "province",
      "cities": [
        {
          "n": "Siem Reap",
          "la": 13.36,
          "lo": 103.86,
          "fn": "Siem Reap, Siem Reap",
          "s": "Siem Reap"
        },
        {
          "n": "Srŏk Ângkôr Thum",
          "la": 13.58,
          "lo": 103.86,
          "fn": "Srŏk Ângkôr Thum, Siem Reap",
          "s": "Siem Reap"
        },
        {
          "n": "Srŏk Prasat Bakong",
          "la": 13.21,
          "lo": 103.98,
          "fn": "Srŏk Prasat Bakong, Siem Reap",
          "s": "Siem Reap"
        },
        {
          "n": "Svay Leu",
          "la": 13.69,
          "lo": 104.27,
          "fn": "Svay Leu, Siem Reap",
          "s": "Siem Reap"
        },
        {
          "n": "Varin",
          "la": 13.84,
          "lo": 103.9,
          "fn": "Varin, Siem Reap",
          "s": "Siem Reap"
        }
      ]
    },
    {
      "n": "Sihanoukville",
      "la": 10.76,
      "lo": 103.82,
      "sc": "18",
      "t": "province",
      "cities": [
        {
          "n": "Sihanoukville",
          "la": 10.61,
          "lo": 103.53,
          "fn": "Sihanoukville, Sihanoukville",
          "s": "Sihanoukville"
        },
        {
          "n": "Srok Stueng Hav",
          "la": 10.85,
          "lo": 103.74,
          "fn": "Srok Stueng Hav, Sihanoukville",
          "s": "Sihanoukville"
        }
      ]
    },
    {
      "n": "Sihanoukville",
      "la": 10.76,
      "lo": 103.82,
      "sc": "18",
      "t": "province",
      "cities": [
        {
          "n": "Sihanoukville",
          "la": 10.61,
          "lo": 103.53,
          "fn": "Sihanoukville, Sihanoukville",
          "s": "Sihanoukville"
        },
        {
          "n": "Srok Stueng Hav",
          "la": 10.85,
          "lo": 103.74,
          "fn": "Srok Stueng Hav, Sihanoukville",
          "s": "Sihanoukville"
        }
      ]
    },
    {
      "n": "Stung Treng",
      "la": 13.58,
      "lo": 105.97,
      "sc": "19",
      "t": "province",
      "cities": [
        {
          "n": "Srŏk Srêsén",
          "la": 13.61,
          "lo": 106.36,
          "fn": "Srŏk Srêsén, Stung Treng",
          "s": "Stung Treng"
        },
        {
          "n": "Stueng Traeng",
          "la": 13.65,
          "lo": 106.07,
          "fn": "Stueng Traeng, Stung Treng",
          "s": "Stung Treng"
        },
        {
          "n": "Stung Treng",
          "la": 13.53,
          "lo": 105.97,
          "fn": "Stung Treng, Stung Treng",
          "s": "Stung Treng"
        }
      ]
    },
    {
      "n": "Stung Treng",
      "la": 13.58,
      "lo": 105.97,
      "sc": "19",
      "t": "province",
      "cities": [
        {
          "n": "Srŏk Srêsén",
          "la": 13.61,
          "lo": 106.36,
          "fn": "Srŏk Srêsén, Stung Treng",
          "s": "Stung Treng"
        },
        {
          "n": "Stueng Traeng",
          "la": 13.65,
          "lo": 106.07,
          "fn": "Stueng Traeng, Stung Treng",
          "s": "Stung Treng"
        },
        {
          "n": "Stung Treng",
          "la": 13.53,
          "lo": 105.97,
          "fn": "Stung Treng, Stung Treng",
          "s": "Stung Treng"
        }
      ]
    },
    {
      "n": "Svay Rieng",
      "la": 11.14,
      "lo": 105.83,
      "sc": "20",
      "t": "province",
      "cities": [
        {
          "n": "Srŏk Svay Chrŭm",
          "la": 11.11,
          "lo": 105.7,
          "fn": "Srŏk Svay Chrŭm, Svay Rieng",
          "s": "Svay Rieng"
        },
        {
          "n": "Svay Rieng",
          "la": 11.09,
          "lo": 105.8,
          "fn": "Svay Rieng, Svay Rieng",
          "s": "Svay Rieng"
        }
      ]
    },
    {
      "n": "Svay Rieng",
      "la": 11.14,
      "lo": 105.83,
      "sc": "20",
      "t": "province",
      "cities": [
        {
          "n": "Srŏk Svay Chrŭm",
          "la": 11.11,
          "lo": 105.7,
          "fn": "Srŏk Svay Chrŭm, Svay Rieng",
          "s": "Svay Rieng"
        },
        {
          "n": "Svay Rieng",
          "la": 11.09,
          "lo": 105.8,
          "fn": "Svay Rieng, Svay Rieng",
          "s": "Svay Rieng"
        }
      ]
    },
    {
      "n": "Takeo",
      "la": 10.93,
      "lo": 104.8,
      "sc": "21",
      "t": "province",
      "cities": [
        {
          "n": "Krŏng Doun Kaev",
          "la": 10.99,
          "lo": 104.8,
          "fn": "Krŏng Doun Kaev, Takeo",
          "s": "Takeo"
        },
        {
          "n": "Phumĭ Véal Srê",
          "la": 10.98,
          "lo": 104.78,
          "fn": "Phumĭ Véal Srê, Takeo",
          "s": "Takeo"
        },
        {
          "n": "Srŏk Ângkôr Borei",
          "la": 10.99,
          "lo": 104.95,
          "fn": "Srŏk Ângkôr Borei, Takeo",
          "s": "Takeo"
        },
        {
          "n": "Srŏk Borei Cholsar",
          "la": 10.81,
          "lo": 104.99,
          "fn": "Srŏk Borei Cholsar, Takeo",
          "s": "Takeo"
        },
        {
          "n": "Takeo",
          "la": 10.99,
          "lo": 104.78,
          "fn": "Takeo, Takeo",
          "s": "Takeo"
        }
      ]
    },
    {
      "n": "Takeo",
      "la": 10.93,
      "lo": 104.8,
      "sc": "21",
      "t": "province",
      "cities": [
        {
          "n": "Krŏng Doun Kaev",
          "la": 10.99,
          "lo": 104.8,
          "fn": "Krŏng Doun Kaev, Takeo",
          "s": "Takeo"
        },
        {
          "n": "Phumĭ Véal Srê",
          "la": 10.98,
          "lo": 104.78,
          "fn": "Phumĭ Véal Srê, Takeo",
          "s": "Takeo"
        },
        {
          "n": "Srŏk Ângkôr Borei",
          "la": 10.99,
          "lo": 104.95,
          "fn": "Srŏk Ângkôr Borei, Takeo",
          "s": "Takeo"
        },
        {
          "n": "Srŏk Borei Cholsar",
          "la": 10.81,
          "lo": 104.99,
          "fn": "Srŏk Borei Cholsar, Takeo",
          "s": "Takeo"
        },
        {
          "n": "Takeo",
          "la": 10.99,
          "lo": 104.78,
          "fn": "Takeo, Takeo",
          "s": "Takeo"
        }
      ]
    }
  ]
}